<?xml version="1.0" encoding="utf-8" ?>
<dwsync>
<file name="7-lagoons-tour.jpg" server="ftp.happyperutours.com" local="132931454620000000" remote="132955112400000000" Dst="0" />
<file name="7-lagunas-tour.jpg" server="ftp.happyperutours.com" local="132928788140000000" remote="132955112400000000" Dst="0" />
<file name="arequipa-tour.jpg" server="ftp.happyperutours.com" local="132927010580000000" remote="132955112400000000" Dst="0" />
<file name="ausangate-7-lagoons-tour.jpg" server="ftp.happyperutours.com" local="132931455440000000" remote="132955112400000000" Dst="0" />
<file name="ausangate-7-lagoons.jpg" server="ftp.happyperutours.com" local="132931455100000000" remote="132955112400000000" Dst="0" />
<file name="ausangate-tour.jpg" server="ftp.happyperutours.com" local="132931456380000000" remote="132955112400000000" Dst="0" />
<file name="camino-inca.jpg" server="ftp.happyperutours.com" local="132933263700000000" remote="132955112400000000" Dst="0" />
<file name="choquequirao-4-days-tour-cusco-peru.jpg" server="ftp.happyperutours.com" local="132928787340000000" remote="132955112400000000" Dst="0" />
<file name="city-tour-calles-del-cusco.jpg" server="ftp.happyperutours.com" local="132928873500000000" remote="132955112400000000" Dst="0" />
<file name="city-tour-cusco.jpg" server="ftp.happyperutours.com" local="132928866900000000" remote="132955112400000000" Dst="0" />
<file name="city-tour-koricancha-jardines.jpg" server="ftp.happyperutours.com" local="132928867180000000" remote="132955112400000000" Dst="0" />
<file name="city-tour-plaza-de-armas.jpg" server="ftp.happyperutours.com" local="132927220640000000" remote="132955112400000000" Dst="0" />
<file name="city-tour-qoricancha-sincretismo.jpg" server="ftp.happyperutours.com" local="132927221300000000" remote="132955112400000000" Dst="0" />
<file name="city-tour-qoricancha.jpg" server="ftp.happyperutours.com" local="132927180840000000" remote="132955112400000000" Dst="0" />
<file name="city-tour-sacsayhuaman.jpg" server="ftp.happyperutours.com" local="132927220960000000" remote="132955112400000000" Dst="0" />
<file name="city-tour-tambomachay-fuente.jpg" server="ftp.happyperutours.com" local="132927221880000000" remote="132955112400000000" Dst="0" />
<file name="city-tour-tambomachay.jpg" server="ftp.happyperutours.com" local="132927221600000000" remote="132955112400000000" Dst="0" />
<file name="happy-cusco-exclusive.jpg" server="ftp.happyperutours.com" local="132928827120000000" remote="132955113000000000" Dst="0" />
<file name="happy-cusco-experience.jpg" server="ftp.happyperutours.com" local="132928826380000000" remote="132955113000000000" Dst="0" />
<file name="happy-cusco-tour.jpg" server="ftp.happyperutours.com" local="132928826780000000" remote="132955113000000000" Dst="0" />
<file name="happy-experience-cusco.jpg" server="ftp.happyperutours.com" local="132928825660000000" remote="132955113000000000" Dst="0" />
<file name="happy-experience-tour-cusco-peru.jpg" server="ftp.happyperutours.com" local="132928787860000000" remote="132955113000000000" Dst="0" />
<file name="happy-experience-tour.jpg" server="ftp.happyperutours.com" local="132928825280000000" remote="132955113000000000" Dst="0" />
<file name="happy-experience.jpg" server="ftp.happyperutours.com" local="132928824940000000" remote="132955113000000000" Dst="0" />
<file name="cusco-amazing-view.png" server="ftp.happyperutours.com" local="132928786860000000" remote="132955113000000000" Dst="0" />
<file name="humantay-lake.jpg" server="ftp.happyperutours.com" local="132931174660000000" remote="132955113000000000" Dst="0" />
<file name="inca-trail-first-class-tour.jpg" server="ftp.happyperutours.com" local="132923824520000000" remote="132955113000000000" Dst="0" />
<file name="lares-caminata-4-dias.jpg" server="ftp.happyperutours.com" local="132928792900000000" remote="132955113000000000" Dst="0" />
<file name="lares-tour-peru.jpg" server="ftp.happyperutours.com" local="132928792240000000" remote="132955113000000000" Dst="0" />
<file name="lares-tour-4-days.jpg" server="ftp.happyperutours.com" local="132928788880000000" remote="132955113000000000" Dst="0" />
<file name="lares-trek-tour.jpg" server="ftp.happyperutours.com" local="132928787620000000" remote="132955113000000000" Dst="0" />
<file name="lima-cuidad-de-reyes.jpg" server="ftp.happyperutours.com" local="132927013580000000" remote="132955113000000000" Dst="0" />
<file name="salkantay-adventure.jpg" server="ftp.happyperutours.com" local="132928848060000000" remote="132955113000000000" Dst="0" />
<file name="salkantay-start-trek.jpg" server="ftp.happyperutours.com" local="132928848420000000" remote="132955113000000000" Dst="0" />
<file name="salkantay-tour.jpg" server="ftp.happyperutours.com" local="132928847120000000" remote="132955113000000000" Dst="0" />
<file name="salkantay-tour-trek.jpg" server="ftp.happyperutours.com" local="132928847760000000" remote="132955113000000000" Dst="0" />
<file name="salkantay-trek.jpg" server="ftp.happyperutours.com" local="132928847440000000" remote="132955113000000000" Dst="0" />
<file name="short-inca-trek-to-machu-picchu.jpg" server="ftp.happyperutours.com" local="132928787740000000" remote="132955113600000000" Dst="0" />
<file name="tour-7-lagoon.jpg" server="ftp.happyperutours.com" local="132931455960000000" remote="132955113600000000" Dst="0" />
<file name="tour-a-lares.jpg" server="ftp.happyperutours.com" local="132928790520000000" remote="132955113600000000" Dst="0" />
<file name="tour-en-lares.jpg" server="ftp.happyperutours.com" local="132928790960000000" remote="132955113600000000" Dst="0" />
<file name="tour-humantay-laguna.jpg" server="ftp.happyperutours.com" local="132931175900000000" remote="132955113600000000" Dst="0" />
<file name="tour-humantay-soroypampa.jpg" server="ftp.happyperutours.com" local="132931175460000000" remote="132955113600000000" Dst="0" />
<file name="tour-humantay-turista.jpg" server="ftp.happyperutours.com" local="132931175080000000" remote="132955113600000000" Dst="0" />
<file name="tour-lares-4-days-peru.jpg" server="ftp.happyperutours.com" local="132928787460000000" remote="132955113600000000" Dst="0" />
<file name="tour-machu-picchu-andenes.jpg" server="ftp.happyperutours.com" local="132928868720000000" remote="132955113600000000" Dst="0" />
<file name="tour-machu-picchu-panoramico.jpg" server="ftp.happyperutours.com" local="132928873120000000" remote="132955113600000000" Dst="0" />
<file name="tour-valle-sagrado-ollantaytambo-fortaleza-inca.jpg" server="ftp.happyperutours.com" local="132928872760000000" remote="132955113600000000" Dst="0" />
<file name="tour-valle-sagrado-chinchero-templo-exterior.jpg" server="ftp.happyperutours.com" local="132928871360000000" remote="132955113600000000" Dst="0" />
<file name="tour-valle-sagrado-pisaq-ruinas.jpg" server="ftp.happyperutours.com" local="132928872400000000" remote="132955113600000000" Dst="0" />
<file name="trekking-salkantay-arribo.jpg" server="ftp.happyperutours.com" local="132931174220000000" remote="132955113600000000" Dst="0" />
<file name="VOYAGER-tour-by-train-in-peru.png" server="ftp.happyperutours.com" local="132928786980000000" remote="132955113600000000" Dst="0" />
<file name="traditional-city-tour.jpg" server="ftp.happyperutours.com" local="132928786600000000" remote="132955113600000000" Dst="0" />
<file name="camino-inca-machu-picchu.jpg" server="ftp.happyperutours.com" local="132933262340000000" remote="132955112400000000" Dst="0" />
<file name="camino-inca-tour.jpg" server="ftp.happyperutours.com" local="132933263500000000" remote="132955112400000000" Dst="0" />
<file name="hiram-bingham-train-tour.jpg" server="ftp.happyperutours.com" local="132932910740000000" remote="132955113000000000" Dst="0" />
<file name="hiram-bingham-train.jpg" server="ftp.happyperutours.com" local="132932891580000000" remote="132955113000000000" Dst="0" />
<file name="hiram-bingham.jpg" server="ftp.happyperutours.com" local="132932892180000000" remote="132955113000000000" Dst="0" />
<file name="inca-trail-tour.jpg" server="ftp.happyperutours.com" local="132933263100000000" remote="132955113000000000" Dst="0" />
<file name="inca-trail.jpg" server="ftp.happyperutours.com" local="132933263280000000" remote="132955113000000000" Dst="0" />
<file name="short-inca-trail.jpg" server="ftp.happyperutours.com" local="132933281720000000" remote="132955113600000000" Dst="0" />
<file name="tour-machu-picchu-andenes-asombrosos.jpg" server="ftp.happyperutours.com" local="132932910080000000" remote="132955113600000000" Dst="0" />
<file name="tour-machu-picchu-sorprendente.jpg" server="ftp.happyperutours.com" local="132932910520000000" remote="132955113600000000" Dst="0" />
<file name="turistas-camino-inca.jpg" server="ftp.happyperutours.com" local="132933262660000000" remote="132955113600000000" Dst="0" />
<file name="7-lagoons-tour.webp" server="ftp.happyperutours.com" local="132937404040000000" remote="132955112400000000" Dst="0" />
<file name="7-lagunas-tour.webp" server="ftp.happyperutours.com" local="132937404060000000" remote="132955112400000000" Dst="0" />
<file name="arequipa-tour.webp" server="ftp.happyperutours.com" local="132937404080000000" remote="132955112400000000" Dst="0" />
<file name="ausangate-7-lagoons-tour_11zon.webp" server="ftp.happyperutours.com" local="132937404160000000" remote="132955112400000000" Dst="0" />
<file name="ausangate-tour_11zon.webp" server="ftp.happyperutours.com" local="132937404180000000" remote="132955112400000000" Dst="0" />
<file name="camino-choquequirao.jpg" server="ftp.happyperutours.com" local="132936749340000000" remote="132955112400000000" Dst="0" />
<file name="choquequirao-tour-4-days.jpg" server="ftp.happyperutours.com" local="132936749020000000" remote="132955112400000000" Dst="0" />
<file name="choquequirao-tour-4-days_11zon.webp" server="ftp.happyperutours.com" local="132937404720000000" remote="132955112400000000" Dst="0" />
<file name="choquequirao.jpg" server="ftp.happyperutours.com" local="132936748500000000" remote="132955112400000000" Dst="0" />
<file name="choquequirao_11zon.webp" server="ftp.happyperutours.com" local="132937404660000000" remote="132955112400000000" Dst="0" />
<file name="city-tour-calles-del-cusco_11zon.webp" server="ftp.happyperutours.com" local="132937404740000000" remote="132955112400000000" Dst="0" />
<file name="city-tour-cusco_11zon.webp" server="ftp.happyperutours.com" local="132937405600000000" remote="132955112400000000" Dst="0" />
<file name="city-tour-koricancha-jardines_11zon.webp" server="ftp.happyperutours.com" local="132937405620000000" remote="132955112400000000" Dst="0" />
<file name="city-tour-plaza-de-armas_11zon.webp" server="ftp.happyperutours.com" local="132937405640000000" remote="132955112400000000" Dst="0" />
<file name="city-tour-qoricancha-sincretismo_11zon.webp" server="ftp.happyperutours.com" local="132937405680000000" remote="132955112400000000" Dst="0" />
<file name="city-tour-qoricancha_11zon.webp" server="ftp.happyperutours.com" local="132937405640000000" remote="132955112400000000" Dst="0" />
<file name="city-tour-sacsayhuaman_11zon.webp" server="ftp.happyperutours.com" local="132937405700000000" remote="132955112400000000" Dst="0" />
<file name="city-tour-tambomachay-fuente_11zon.webp" server="ftp.happyperutours.com" local="132937405720000000" remote="132955112400000000" Dst="0" />
<file name="city-tour-tambomachay_11zon.webp" server="ftp.happyperutours.com" local="132937405700000000" remote="132955112400000000" Dst="0" />
<file name="cueva-huchuy-qosqo.jpg" server="ftp.happyperutours.com" local="132936762420000000" remote="132955112400000000" Dst="0" />
<file name="cueva-huchuy-qosqo_11zon.webp" server="ftp.happyperutours.com" local="132937406040000000" remote="132955113000000000" Dst="0" />
<file name="happy-city-tour-cusco.jpg" server="ftp.happyperutours.com" local="132933329180000000" remote="132955113000000000" Dst="0" />
<file name="cusco-amazing-view_11zon.webp" server="ftp.happyperutours.com" local="132937406060000000" remote="132955113000000000" Dst="0" />
<file name="happy-city-tour-cusco_11zon.webp" server="ftp.happyperutours.com" local="132937406080000000" remote="132955113000000000" Dst="0" />
<file name="happy-cusco-exclusive_11zon.webp" server="ftp.happyperutours.com" local="132937406100000000" remote="132955113000000000" Dst="0" />
<file name="happy-cusco-experience_11zon.webp" server="ftp.happyperutours.com" local="132937406120000000" remote="132955113000000000" Dst="0" />
<file name="happy-cusco-tour_11zon.webp" server="ftp.happyperutours.com" local="132937406140000000" remote="132955113000000000" Dst="0" />
<file name="happy-experience-cusco_11zon.webp" server="ftp.happyperutours.com" local="132937406160000000" remote="132955113000000000" Dst="0" />
<file name="happy-experience-tour-cusco-peru_11zon.webp" server="ftp.happyperutours.com" local="132937406500000000" remote="132955113000000000" Dst="0" />
<file name="happy-experience-tour_11zon.webp" server="ftp.happyperutours.com" local="132937406480000000" remote="132955113600000000" Dst="0" />
<file name="happy-experience_11zon.webp" server="ftp.happyperutours.com" local="132937406140000000" remote="132955113000000000" Dst="0" />
<file name="hiram-bingham-train_11zon.webp" server="ftp.happyperutours.com" local="132937406520000000" remote="132955113000000000" Dst="0" />
<file name="hiram-bingham_11zon.webp" server="ftp.happyperutours.com" local="132937406520000000" remote="132955113000000000" Dst="0" />
<file name="huchuy-qosqo-tour-2-days.jpg" server="ftp.happyperutours.com" local="132936762120000000" remote="132955113000000000" Dst="0" />
<file name="huchuy-qosqo-tour.jpg" server="ftp.happyperutours.com" local="132936761400000000" remote="132955113000000000" Dst="0" />
<file name="huchuy-qosqo-tour_11zon.webp" server="ftp.happyperutours.com" local="132937406580000000" remote="132955113000000000" Dst="0" />
<file name="inca-jungle-4-days.jpg" server="ftp.happyperutours.com" local="132936786400000000" remote="132955113000000000" Dst="0" />
<file name="inca-jungle-4-days_11zon.webp" server="ftp.happyperutours.com" local="132937407000000000" remote="132955113000000000" Dst="0" />
<file name="inca-jungle-tour.jpg" server="ftp.happyperutours.com" local="132936785700000000" remote="132955113000000000" Dst="0" />
<file name="inca-trail-first-class-tour_11zon.webp" server="ftp.happyperutours.com" local="132937407060000000" remote="132955113000000000" Dst="0" />
<file name="inca-jungle-tour_11zon.webp" server="ftp.happyperutours.com" local="132937407020000000" remote="132955113000000000" Dst="0" />
<file name="inca-trail-tour_11zon.webp" server="ftp.happyperutours.com" local="132937407080000000" remote="132955113000000000" Dst="0" />
<file name="inca-trail_11zon.webp" server="ftp.happyperutours.com" local="132937407040000000" remote="132955113000000000" Dst="0" />
<file name="inka-jungle-tour.jpg" server="ftp.happyperutours.com" local="132936786000000000" remote="132955113000000000" Dst="0" />
<file name="inka-jungle-tour_11zon.webp" server="ftp.happyperutours.com" local="132937407100000000" remote="132955113000000000" Dst="0" />
<file name="lares-caminata-4-dias_11zon.webp" server="ftp.happyperutours.com" local="132937407120000000" remote="132955113000000000" Dst="0" />
<file name="lares-tour-4-days_11zon.webp" server="ftp.happyperutours.com" local="132937407120000000" remote="132955113000000000" Dst="0" />
<file name="lares-tour-peru_11zon.webp" server="ftp.happyperutours.com" local="132937407420000000" remote="132955113000000000" Dst="0" />
<file name="lares-trek-tour_11zon.webp" server="ftp.happyperutours.com" local="132937407440000000" remote="132955113000000000" Dst="0" />
<file name="machu-picchu-sacred-valley.jpg" server="ftp.happyperutours.com" local="132936807040000000" remote="132955113000000000" Dst="0" />
<file name="lima-cuidad-de-reyes_11zon.webp" server="ftp.happyperutours.com" local="132937407460000000" remote="132955113000000000" Dst="0" />
<file name="machu-picchu-sacred-valley_11zon.webp" server="ftp.happyperutours.com" local="132937407480000000" remote="132955113000000000" Dst="0" />
<file name="pollo-a-la-brasa.jpg" server="ftp.happyperutours.com" local="132933324900000000" remote="132955113000000000" Dst="0" />
<file name="pollo-a-la-brasa_11zon.webp" server="ftp.happyperutours.com" local="132937407500000000" remote="132955113000000000" Dst="0" />
<file name="pueblo-de-cuyes.jpg" server="ftp.happyperutours.com" local="132936008780000000" remote="132955113000000000" Dst="0" />
<file name="pueblo-de-cuyes_11zon.webp" server="ftp.happyperutours.com" local="132937407520000000" remote="132955113000000000" Dst="0" />
<file name="puente-choquequirao.jpg" server="ftp.happyperutours.com" local="132936749960000000" remote="132955113000000000" Dst="0" />
<file name="puente-choquequirao_11zon.webp" server="ftp.happyperutours.com" local="132937407520000000" remote="132955113000000000" Dst="0" />
<file name="sacred-valley-3-days-tour.jpg" server="ftp.happyperutours.com" local="132936797220000000" remote="132955113000000000" Dst="0" />
<file name="sacred-valley-3-days-tour_11zon.webp" server="ftp.happyperutours.com" local="132937407720000000" remote="132955113000000000" Dst="0" />
<file name="sacred-valley-3-days.jpg" server="ftp.happyperutours.com" local="132936796900000000" remote="132955113000000000" Dst="0" />
<file name="sacred-valley-3-days_11zon.webp" server="ftp.happyperutours.com" local="132937407540000000" remote="132955113000000000" Dst="0" />
<file name="sacred-valley-tour.jpg" server="ftp.happyperutours.com" local="132936795900000000" remote="132955113000000000" Dst="0" />
<file name="sacred-valley-tour_11zon.webp" server="ftp.happyperutours.com" local="132937407740000000" remote="132955113000000000" Dst="0" />
<file name="salkantay-adventure_11zon.webp" server="ftp.happyperutours.com" local="132937407760000000" remote="132955113000000000" Dst="0" />
<file name="salkantay-start-trek_11zon.webp" server="ftp.happyperutours.com" local="132937407780000000" remote="132955113000000000" Dst="0" />
<file name="salkantay-trek_11zon.webp" server="ftp.happyperutours.com" local="132937407820000000" remote="132955113000000000" Dst="0" />
<file name="short-inca-trail-to-machu-picchu.jpg" server="ftp.happyperutours.com" local="132936796580000000" remote="132955113000000000" Dst="0" />
<file name="short-inca-trail-to-machu-picchu_11zon.webp" server="ftp.happyperutours.com" local="132937408080000000" remote="132955113000000000" Dst="0" />
<file name="short-inca-trail_11zon.webp" server="ftp.happyperutours.com" local="132937407840000000" remote="132955113600000000" Dst="0" />
<file name="short-inca-trek-to-machu-picchu_11zon.webp" server="ftp.happyperutours.com" local="132937408100000000" remote="132955113600000000" Dst="0" />
<file name="tour-7-lagoon_11zon.webp" server="ftp.happyperutours.com" local="132937408100000000" remote="132955113600000000" Dst="0" />
<file name="tour-a-lares_11zon.webp" server="ftp.happyperutours.com" local="132937408120000000" remote="132955113600000000" Dst="0" />
<file name="tour-en-lares_11zon.webp" server="ftp.happyperutours.com" local="132937408160000000" remote="132955113600000000" Dst="0" />
<file name="tour-en-maras-moray.jpg" server="ftp.happyperutours.com" local="132936012980000000" remote="132955113600000000" Dst="0" />
<file name="tour-en-maras-moray_11zon.webp" server="ftp.happyperutours.com" local="132937408160000000" remote="132955113600000000" Dst="0" />
<file name="tour-humantay-laguna_11zon.webp" server="ftp.happyperutours.com" local="132937408180000000" remote="132955113600000000" Dst="0" />
<file name="tour-humantay-soroypampa_11zon.webp" server="ftp.happyperutours.com" local="132937408200000000" remote="132955113600000000" Dst="0" />
<file name="tour-humantay-turista_11zon.webp" server="ftp.happyperutours.com" local="132937408580000000" remote="132955113600000000" Dst="0" />
<file name="tour-lares-4-days-peru_11zon.webp" server="ftp.happyperutours.com" local="132937408600000000" remote="132955113600000000" Dst="0" />
<file name="tour-machu-picchu-andenes-asombrosos_11zon.webp" server="ftp.happyperutours.com" local="132937408640000000" remote="132955113600000000" Dst="0" />
<file name="tour-machu-picchu-panoramico_11zon.webp" server="ftp.happyperutours.com" local="132937408660000000" remote="132955113600000000" Dst="0" />
<file name="tour-valle-sagrado-chinchero-templo-exterior_11zon.webp" server="ftp.happyperutours.com" local="132937408700000000" remote="132955113600000000" Dst="0" />
<file name="tour-valle-sagrado-maras-extraccion-de-sal.jpg" server="ftp.happyperutours.com" local="132936007200000000" remote="132955113600000000" Dst="0" />
<file name="tour-valle-sagrado-maras-extraccion-de-sal_11zon.webp" server="ftp.happyperutours.com" local="132937408940000000" remote="132955113600000000" Dst="0" />
<file name="tour-valle-sagrado-maras-panoramico.jpg" server="ftp.happyperutours.com" local="132936006960000000" remote="132955113600000000" Dst="0" />
<file name="tour-valle-sagrado-maras.jpg" server="ftp.happyperutours.com" local="132936007460000000" remote="132955113600000000" Dst="0" />
<file name="tour-valle-sagrado-moray-andenes.jpg" server="ftp.happyperutours.com" local="132935994360000000" remote="132955113600000000" Dst="0" />
<file name="tour-valle-sagrado-moray.jpg" server="ftp.happyperutours.com" local="132936013360000000" remote="132955113600000000" Dst="0" />
<file name="tour-valle-sagrado-moray_11zon.webp" server="ftp.happyperutours.com" local="132937408980000000" remote="132955113600000000" Dst="0" />
<file name="tour-valle-sagrado-ollantaytambo-fortaleza-inca_11zon.webp" server="ftp.happyperutours.com" local="132937409000000000" remote="132955113600000000" Dst="0" />
<file name="tour-valle-sagrado-ollantaytambo-pinkuylluna.jpg" server="ftp.happyperutours.com" local="132933364840000000" remote="132955113600000000" Dst="0" />
<file name="tour-valle-sagrado-ollantaytambo-pinkuylluna_11zon.webp" server="ftp.happyperutours.com" local="132937409020000000" remote="132955113600000000" Dst="0" />
<file name="tour-valle-sagrado-pisaq-andenes.jpg" server="ftp.happyperutours.com" local="132933364180000000" remote="132955113600000000" Dst="0" />
<file name="tour-valle-sagrado-pisaq-andenes_11zon.webp" server="ftp.happyperutours.com" local="132937409220000000" remote="132955113600000000" Dst="0" />
<file name="tour-valle-sagrado-pisaq-ruinas_11zon.webp" server="ftp.happyperutours.com" local="132937409240000000" remote="132955113600000000" Dst="0" />
<file name="tour-valle-sagrado-pisaq.jpg" server="ftp.happyperutours.com" local="132933363700000000" remote="132955113600000000" Dst="0" />
<file name="tour-valle-sagrado-pisaq_11zon.webp" server="ftp.happyperutours.com" local="132937409040000000" remote="132955113600000000" Dst="0" />
<file name="traditional-city-tour_11zon.webp" server="ftp.happyperutours.com" local="132937409260000000" remote="132955113600000000" Dst="0" />
<file name="turistas-camino-inca_11zon.webp" server="ftp.happyperutours.com" local="132937409300000000" remote="132955113600000000" Dst="0" />
<file name="visit-huchuy-qosqo.jpg" server="ftp.happyperutours.com" local="132936761820000000" remote="132955113600000000" Dst="0" />
<file name="trekking-salkantay-arribo_11zon.webp" server="ftp.happyperutours.com" local="132937409260000000" remote="132955113600000000" Dst="0" />
<file name="visit-huchuy-qosqo_11zon.webp" server="ftp.happyperutours.com" local="132937409300000000" remote="132955113600000000" Dst="0" />
<file name="fauna-llamas-vinicunca.jpg" server="ftp.happyperutours.com" local="132937585640000000" remote="132955113000000000" Dst="0" />
<file name="montana-de-colores-trekking.jpg" server="ftp.happyperutours.com" local="132937582620000000" remote="132955113000000000" Dst="0" />
<file name="qeswachaca-bridge.jpg" server="ftp.happyperutours.com" local="132937576600000000" remote="132955113000000000" Dst="0" />
<file name="QESWACHACA.jpg" server="ftp.happyperutours.com" local="132937576740000000" remote="132955113000000000" Dst="0" />
<file name="turista en-vinicunca.jpg" server="ftp.happyperutours.com" local="132937585460000000" remote="132955113600000000" Dst="0" />
<file name="vinicunca-7-colores.jpg" server="ftp.happyperutours.com" local="132937584440000000" remote="132955113600000000" Dst="0" />
<file name="waqrapucara-full-day-tour.jpg" server="ftp.happyperutours.com" local="132937639860000000" remote="132955113600000000" Dst="0" />
<file name="waqrapukara-cusco-tour.jpg" server="ftp.happyperutours.com" local="132937640220000000" remote="132955113600000000" Dst="0" />
<file name="waqrapukara-happy-peru.jpg" server="ftp.happyperutours.com" local="132939202000000000" remote="132955113600000000" Dst="0" />
<file name="waqrapukara-tour-full-day.jpg" server="ftp.happyperutours.com" local="132937639360000000" remote="132955113600000000" Dst="0" />
<file name="hiram-bingham-train-tour.webp" server="ftp.happyperutours.com" local="132937406560000000" remote="132955113000000000" Dst="0" />
<file name="inca-rail-first-class.jpg" server="ftp.happyperutours.com" local="132939387260000000" remote="132955113000000000" Dst="0" />
<file name="inca-rail-fisrt-class-tour.jpg" server="ftp.happyperutours.com" local="132939387600000000" remote="132955113000000000" Dst="0" />
<file name="inca-rail-voyager-train.jpg" server="ftp.happyperutours.com" local="132939394780000000" remote="132955113000000000" Dst="0" />
<file name="inca-rail-voyager.jpg" server="ftp.happyperutours.com" local="132939394440000000" remote="132955113000000000" Dst="0" />
<file name="inca-train-360-tour.jpg" server="ftp.happyperutours.com" local="132939367880000000" remote="132955113000000000" Dst="0" />
<file name="inca-train-360-train-tour.jpg" server="ftp.happyperutours.com" local="132939368240000000" remote="132955113000000000" Dst="0" />
<file name="inca-train-360.JPG" server="ftp.happyperutours.com" local="132939367180000000" remote="132955113000000000" Dst="0" />
<file name="perurail-expedition.jpg" server="ftp.happyperutours.com" local="132939408880000000" remote="132955113000000000" Dst="0" />
<file name="perurail-sacred-valley-tour.jpg" server="ftp.happyperutours.com" local="132939419220000000" remote="132955113000000000" Dst="0" />
<file name="perurail-sacred-valley.jpg" server="ftp.happyperutours.com" local="132939418920000000" remote="132955113000000000" Dst="0" />
<file name="perurail-vistadome-tour-train.jpg" server="ftp.happyperutours.com" local="132939435940000000" remote="132955113000000000" Dst="0" />
<file name="perurail-vistadome-train-tour.jpg" server="ftp.happyperutours.com" local="132939437000000000" remote="132955113000000000" Dst="0" />
<file name="perurail-vistadome.jpg" server="ftp.happyperutours.com" local="132939435600000000" remote="132955113000000000" Dst="0" />
<file name="tour-machu-picchu-andenes.webp" server="ftp.happyperutours.com" local="132937408620000000" remote="132955113600000000" Dst="0" />
<file name="tour-machu-picchu-panoramico-chullito.png" server="ftp.happyperutours.com" local="132939369080000000" remote="132955113600000000" Dst="0" />
<file name="tour-machu-picchu-llama.png" server="ftp.happyperutours.com" local="132939395320000000" remote="132955113600000000" Dst="0" />
<file name="tour-machu-picchu-partida.png" server="ftp.happyperutours.com" local="132939408360000000" remote="132955113600000000" Dst="0" />
<file name="tour-machu-picchu-ruinas.png" server="ftp.happyperutours.com" local="132939368740000000" remote="132955113600000000" Dst="0" />
<file name="trek-to-waqrapucara.jpg" server="ftp.happyperutours.com" local="132939201060000000" remote="132955113600000000" Dst="0" />
<file name="waqrapukara-tour.jpg" server="ftp.happyperutours.com" local="132939201700000000" remote="132955113600000000" Dst="0" />
<file name="tour-valle-sagrado-moray-andenes.webp" server="ftp.happyperutours.com" local="132937409000000000" remote="132955113600000000" Dst="0" />
<file name="ausangate-7-lagoons.webp" server="ftp.happyperutours.com" local="132937404120000000" remote="132955112400000000" Dst="0" />
<file name="camino-choquequirao.webp" server="ftp.happyperutours.com" local="132937404220000000" remote="132955112400000000" Dst="0" />
<file name="camino-inca-machu-picchu.webp" server="ftp.happyperutours.com" local="132937404620000000" remote="132955112400000000" Dst="0" />
<file name="camino-inca-tour.webp" server="ftp.happyperutours.com" local="132937404640000000" remote="132955112400000000" Dst="0" />
<file name="camino-inca.webp" server="ftp.happyperutours.com" local="132937404580000000" remote="132955112400000000" Dst="0" />
<file name="choquequirao-4-days-tour-cusco-peru.webp" server="ftp.happyperutours.com" local="132937404700000000" remote="132955112400000000" Dst="0" />
<file name="huchuy-qosqo-tour-2-days.webp" server="ftp.happyperutours.com" local="132937406600000000" remote="132955113000000000" Dst="0" />
<file name="humantay-lake.webp" server="ftp.happyperutours.com" local="132937406620000000" remote="132955113000000000" Dst="0" />
<file name="inca-train-360.webp" server="ftp.happyperutours.com" local="132954846227541766" remote="132955113000000000" Dst="0" />
<file name="montana-de-colores-trekking.webp" server="ftp.happyperutours.com" local="132954828320009728" remote="132955113000000000" Dst="0" />
<file name="qeswachaca-bridge.webp" server="ftp.happyperutours.com" local="132954823402595676" remote="132955113000000000" Dst="0" />
<file name="sacred-valley-of-the-incas.jpg" server="ftp.happyperutours.com" local="132954754289272693" remote="132955113000000000" Dst="0" />
<file name="sacred-valley-of-the-incas.webp" server="ftp.happyperutours.com" local="132954754516417924" remote="132955113000000000" Dst="0" />
<file name="salkantay-tour-trek.webp" server="ftp.happyperutours.com" local="132937407800000000" remote="132955113000000000" Dst="0" />
<file name="salkantay-tour.webp" server="ftp.happyperutours.com" local="132937407800000000" remote="132955113000000000" Dst="0" />
<file name="tour-machu-picchu-panoramico-chullito.webp" server="ftp.happyperutours.com" local="132954771485705135" remote="132955113600000000" Dst="0" />
<file name="tour-machu-picchu-sorprendente.webp" server="ftp.happyperutours.com" local="132937408680000000" remote="132955113600000000" Dst="0" />
<file name="tour-valle-sagrado-maras-panoramico.webp" server="ftp.happyperutours.com" local="132937408960000000" remote="132955113600000000" Dst="0" />
<file name="tour-valle-sagrado-maras.webp" server="ftp.happyperutours.com" local="132937408920000000" remote="132955113600000000" Dst="0" />
<file name="waqrapukara-happy-peru.webp" server="ftp.happyperutours.com" local="132954830604096911" remote="132955113600000000" Dst="0" />
<file name="inca-rail-fisrt-class-tour.webp" server="ftp.happyperutours.com" local="132955784834605972" remote="132959062200000000" Dst="0" />
<file name="perurail-expedition.webp" server="ftp.happyperutours.com" local="132955788715314860" remote="132959062200000000" Dst="0" />
<file name="perurail-vistadome.webp" server="ftp.happyperutours.com" local="132955791198343581" remote="132959062200000000" Dst="0" />
<file name="trek-to-rainbow-mountain.webp" server="ftp.happyperutours.com" local="132956581531191870" remote="132959062200000000" Dst="0" />
<file name="VOYAGER-tour-by-train-in-peru.webp" server="ftp.happyperutours.com" local="132937409320000000" remote="132959062200000000" Dst="0" />
<file name="tour-puno-peru.webp" server="ftp.happyperutours.com" local="132937408680000000" remote="132978285600000000" Dst="0" />
</dwsync>